{
    "main_tasks": [
        {
            "name": "Name 1",
            "sub_tasks": [
                {
                    "name": "sub name 1"
                },
                {
                    "name": "sub name 2"
                },
                {
                    "name": "sub name 3"
                }
            ],
            "notes": ""
        },
        {
            "name": "Name 2",
            "sub_tasks": [],
            "notes": ""
        },
        {
            "name": "Name 3",
            "sub_tasks": [],
            "notes": ""
        },
        {
            "name": "Name 4",
            "sub_tasks": [],
            "notes": ""
        },
        {
            "name": "name 5",
            "sub_tasks": [],
            "notes": ""
        }
    ]
}